Lab1/blackbox.v
module blackbox(l, j, v, f);
    output l;
    input  j, v, f;
    wire   w01, w15, w16, w17, w24, w45, w48, w51, w57, w67, w80, w82, w85, w87, w88, w98;
    or  o18(l, w88, w45);
    and a22(w88, w51, w57);
    or  o77(w57, w82, w17);
    not n95(w82, w17);
    and a58(w45, w24, w15);
    not n27(w15, w24);
    and a56(w17, w16, w85);
    not n74(w16, j);
    or  o94(w85, v, f);
    or  o96(w24, w67, w48);
    and a41(w67, w98, f);
    not n69(w98, v);
    and a39(w48, f, v, j);
    and a14(w51, f, w87);
    or  o81(w87, w01, w80);
    not n71(w01, v);
    and a38(w80, j, v);
endmodule // blackbox

Lab1/blackbox_tb.v
module blackbox_test;
	reg a,b,c;
	wire cout;
	blackbox bl(cout,a,b,c);
	initial begin
		$dumpfile("blackbox.vcd");
		$dumpvars(0,blackbox_test);

		a=0;b=0;c=0; # 10;
		a=1;b=0;c=0; # 10;
		a=0;b=1;c=0; # 10;
		a=0;b=0;c=1; # 10;
		a=1;b=1;c=0; # 10;
		a=1;b=0;c=1; # 10;
		a=0;b=1;c=1; # 10;
		a=1;b=1;c=1; # 10;
	end
	initial
        $monitor("At time %2t, a = %d b = %d c = %d cout = %d",
                 $time, a, b, c , cout);
endmodule // blackbox_test

Lab1/blackbox.vcd
$date
	Sat Jan 20 20:14:36 2018
$end
$version
	Icarus Verilog
$end
$timescale
	1s
$end
$scope module blackbox_test $end
$var wire 1 ! cout $end
$var reg 1 " a $end
$var reg 1 # b $end
$var reg 1 $ c $end
$scope module bl $end
$var wire 1 $ f $end
$var wire 1 " j $end
$var wire 1 ! l $end
$var wire 1 # v $end
$var wire 1 % w01 $end
$var wire 1 & w15 $end
$var wire 1 ' w16 $end
$var wire 1 ( w17 $end
$var wire 1 ) w24 $end
$var wire 1 * w45 $end
$var wire 1 + w48 $end
$var wire 1 , w51 $end
$var wire 1 - w57 $end
$var wire 1 . w67 $end
$var wire 1 / w80 $end
$var wire 1 0 w82 $end
$var wire 1 1 w85 $end
$var wire 1 2 w87 $end
$var wire 1 3 w88 $end
$var wire 1 4 w98 $end
$upscope $end
$upscope $end
$enddefinitions $end
#0
$dumpvars
14
03
12
01
10
0/
0.
1-
0,
0+
0*
0)
0(
1'
1&
1%
0$
0#
0"
0!
$end
#10
0'
1"
#20
00
02
1(
11
04
0%
1'
1#
0"
#30
1!
13
0&
0*
1,
1)
12
1.
14
1%
1$
0#
#40
1&
0!
10
1-
0)
03
0(
0.
0,
04
0%
0'
1/
0$
1#
1"
#50
0&
0*
1!
1)
13
1.
1,
14
1%
0/
1$
0#
#60
0!
1&
03
0)
0,
00
0.
02
1(
04
0%
1'
1#
0"
#70
13
1!
10
1-
0&
0*
1,
0(
1)
12
0'
1+
1/
1"
