Lab3/mux.v
// output = A (when control == 0) or B (when control == 1)
module mux2(out, A, B, control);
    output out;
    input  A, B;
    input  control;
    wire   wA, wB, not_control;
         
    not n1(not_control, control);
    and a1(wA, A, not_control);
    and a2(wB, B, control);
    or  o1(out, wA, wB);
endmodule // mux2

// output = A (when control == 00) or B (when control == 01) or
//          C (when control == 10) or D (when control == 11)
module mux4(out, A, B, C, D, control);
    output      out;
    input       A, B, C, D;
    input [1:0] control;
    wire w1,w2;
    mux2 m1(w1,A,C,control[1]);
    mux2 m2(w2,B,D,control[1]);
    mux2 m3(out,w1,w2,control[0]);
endmodule // mux4

Lab3/logicunit.v
// 00 - AND, 01 - OR, 10 - NOR, 11 - XOR
module logicunit(out, A, B, control);
    output      out;
    input       A, B;
    input [1:0] control;
    wire w1,w2,w3,w4;
    and a1(w1,A,B);
    or o1(w2,A,B);
    nor n1(w3,A,B);
    xor x1(w4,A,B);

    mux4 m1(out,w1,w2,w3,w4,control);

endmodule // logicunit

Lab3/logicunit_tb.v
module logicunit_test;
    // exhaustively test your logic unit by adapting mux4_tb.v
    // 00 - AND, 01 - OR, 10 - NOR, 11 - XOR
    reg a=0;
    always #1 a = !a;
    reg b=0;
    always #2 b = !b;
    reg [1:0] control = 0;
    wire out;
    logicunit l1(out,a,b,control);
    initial begin
    	$dumpfile("logicunit.vcd");
    	$dumpvars(0,logicunit_test);

    	#4 control = 1;
    	#4 control = 2;
    	#4 control = 3;
    	$finish;
    end

endmodule // logicunit_test

Lab3/logicunit.vcd
$date
	Fri Feb  2 00:23:19 2018
$end
$version
	Icarus Verilog
$end
$timescale
	1s
$end
$scope module logicunit_test $end
$var wire 1 ! out $end
$var reg 1 " a $end
$var reg 1 # b $end
$var reg 2 $ control [1:0] $end
$scope module l1 $end
$var wire 1 " A $end
$var wire 1 # B $end
$var wire 2 % control [1:0] $end
$var wire 1 & w1 $end
$var wire 1 ' w2 $end
$var wire 1 ( w3 $end
$var wire 1 ) w4 $end
$var wire 1 ! out $end
$scope module m1 $end
$var wire 1 & A $end
$var wire 1 ' B $end
$var wire 1 ( C $end
$var wire 1 ) D $end
$var wire 2 * control [1:0] $end
$var wire 1 + w2 $end
$var wire 1 , w1 $end
$var wire 1 ! out $end
$scope module m1 $end
$var wire 1 & A $end
$var wire 1 ( B $end
$var wire 1 - control $end
$var wire 1 . not_control $end
$var wire 1 , out $end
$var wire 1 / wA $end
$var wire 1 0 wB $end
$upscope $end
$scope module m2 $end
$var wire 1 ' A $end
$var wire 1 ) B $end
$var wire 1 1 control $end
$var wire 1 2 not_control $end
$var wire 1 + out $end
$var wire 1 3 wA $end
$var wire 1 4 wB $end
$upscope $end
$scope module m3 $end
$var wire 1 , A $end
$var wire 1 + B $end
$var wire 1 5 control $end
$var wire 1 6 not_control $end
$var wire 1 ! out $end
$var wire 1 7 wA $end
$var wire 1 8 wB $end
$upscope $end
$upscope $end
$upscope $end
$upscope $end
$enddefinitions $end
#0
$dumpvars
08
07
16
05
04
03
12
01
00
0/
1.
0-
0,
0+
b0 *
0)
1(
0'
0&
b0 %
b0 $
0#
0"
0!
$end
#1
1+
13
1'
0(
1)
1"
#2
0"
1#
#3
1!
17
1,
1/
1&
0)
1"
#4
0!
0,
0+
07
0/
03
06
08
0&
0'
1(
15
0"
0#
b1 $
b1 %
b1 *
#5
1!
18
1+
13
1'
0(
1)
1"
#6
0"
1#
#7
1,
1/
1&
0)
1"
#8
0+
17
1!
0/
03
0.
10
02
16
08
0&
0'
1(
1-
11
05
0"
0#
b10 $
b10 %
b10 *
#9
0!
07
0,
1+
00
14
1'
0(
1)
1"
#10
0"
1#
#11
0+
04
1&
0)
1"
#12
1,
10
06
0&
0'
1(
15
0"
0#
b11 $
b11 %
b11 *
